selenium_print_external/__init__.py
selenium_print_external/printer.py
selenium_print_external-0.1.2.dist-info/METADATA
selenium_print_external-0.1.2.dist-info/WHEEL
selenium_print_external-0.1.2.dist-info/RECORD
