Metadata-Version: 2.1
Name: selenium-print-external
Version: 0.1.2
Summary: 
Author: Teddy Xinyuan Chen
Author-email: 45612704+tddschn@users.noreply.github.com
Requires-Python: >=3.11
Classifier: Programming Language :: Python :: 3
Classifier: Programming Language :: Python :: 3.11
Classifier: Programming Language :: Python :: 3.12
Classifier: Programming Language :: Python :: 3.13
Requires-Dist: selenium (>=4.30.0,<5.0.0)
Requires-Dist: undetected-chromedriver (>=3.5.5,<4.0.0)
